mylib/__init__.py
mylib/extract.py
mylib/main.py
mylib/query.py
mylib/transform_load.py
complex_sql_tool-1.0.4.dist-info/LICENSE
complex_sql_tool-1.0.4.dist-info/METADATA
complex_sql_tool-1.0.4.dist-info/WHEEL
complex_sql_tool-1.0.4.dist-info/entry_points.txt
complex_sql_tool-1.0.4.dist-info/top_level.txt
complex_sql_tool-1.0.4.dist-info/RECORD
