Metadata-Version: 2.1
Name: complex-sql-tool
Version: 1.0.4
Summary: A toy tool for IDS706 to run complex SQL with external MYSQL database.
Home-page: https://github.com/nogibjj/IDS706_package_python_CLI
Author: Hongji
License-File: LICENSE
Requires-Dist: black >=23.3.0
Requires-Dist: fpdf >=1.7.2
Requires-Dist: matplotlib >=3.5.3
Requires-Dist: pytest >=5.4.0
Requires-Dist: ruff >=0.6.5
Requires-Dist: jupyter >=1.1.1
Requires-Dist: nbval >=0.11.0
Requires-Dist: polars-lts-cpu >=0.18.4
Requires-Dist: mysql-connector-python >=8.0.0
Requires-Dist: tabulate >=0.8.0
Requires-Dist: python-dotenv >=1.0.0
Requires-Dist: pandas >=2.0.0
